hubsante_model/__init__.py
hubsante_model/cisu/models/access.py
hubsante_model/cisu/models/additional_information.py
hubsante_model/cisu/models/alert.py
hubsante_model/cisu/models/attachment.py
hubsante_model/cisu/models/call_taker.py
hubsante_model/cisu/models/caller.py
hubsante_model/cisu/models/city.py
hubsante_model/cisu/models/contact.py
hubsante_model/cisu/models/coord.py
hubsante_model/cisu/models/create_case.py
hubsante_model/cisu/models/create_case_wrapper.py
hubsante_model/cisu/models/custom_map.py
hubsante_model/cisu/models/detailed_address.py
hubsante_model/cisu/models/detailed_name.py
hubsante_model/cisu/models/external_info.py
hubsante_model/cisu/models/external_location_id.py
hubsante_model/cisu/models/geometry.py
hubsante_model/cisu/models/health_motive.py
hubsante_model/cisu/models/location.py
hubsante_model/cisu/models/location_kind.py
hubsante_model/cisu/models/notes.py
hubsante_model/cisu/models/point.py
hubsante_model/cisu/models/qualification.py
hubsante_model/cisu/models/risk_threat.py
hubsante_model/cisu/models/victims.py
hubsante_model/cisu/models/way_name.py
hubsante_model/cisu/models/whats_happen.py
hubsante_model/documentlink/models/document.py
hubsante_model/documentlink/models/document_link.py
hubsante_model/documentlink/models/document_link_wrapper.py
hubsante_model/emsi/models/casualties.py
hubsante_model/emsi/models/contact.py
hubsante_model/emsi/models/context.py
hubsante_model/emsi/models/coord.py
hubsante_model/emsi/models/egeo.py
hubsante_model/emsi/models/emsi.py
hubsante_model/emsi/models/emsi_wrapper.py
hubsante_model/emsi/models/etype.py
hubsante_model/emsi/models/evac.py
hubsante_model/emsi/models/event.py
hubsante_model/emsi/models/external_info.py
hubsante_model/emsi/models/link.py
hubsante_model/emsi/models/mission.py
hubsante_model/emsi/models/origin.py
hubsante_model/emsi/models/position.py
hubsante_model/emsi/models/reference.py
hubsante_model/emsi/models/resource.py
hubsante_model/emsi/models/rgeo.py
hubsante_model-0.1.1.dist-info/METADATA
hubsante_model-0.1.1.dist-info/WHEEL
hubsante_model-0.1.1.dist-info/top_level.txt
hubsante_model-0.1.1.dist-info/RECORD
