Metadata-Version: 2.1
Name: hubsante_model
Version: 0.1.1
Summary: Hub Santé Modèles
Author-email: Romain Fd <romain.fd@gmail.com>, Hub Santé <hubsante.contact@esante.gouv.fr>
Project-URL: Homepage, https://hub.esante.gouv.fr/
Project-URL: Issues, https://github.com/ansforge/SAMU-Hub-Modeles/issues
Classifier: Programming Language :: Python :: 3
Classifier: License :: OSI Approved :: MIT License
Classifier: Operating System :: OS Independent
Requires-Python: >=3.8
